{
  "bard:Strike": {
    "NAME": "Strike",
    "DESCRIPTION": "Deal !D! damage."
  },
  "bard:Defend": {
    "NAME": "Defend",
    "DESCRIPTION": "Gain !B! Block."
  },
  "bard:Inspire": {
    "NAME": "Inspire",
    "DESCRIPTION": "Gain Inspiration !M!. NL Exhaust.",
    "UPGRADE_DESCRIPTION": "Gain Inspiration !M!. NL Exhaustive !stslib:ex!."
  },
  "bard:Riposte": {
    "NAME": "Riposte",
    "DESCRIPTION": "Deal !D! damage. NL Gain !B! Block."
  },
  "bard:Sing": {
    "NAME": "Sing",
    "DESCRIPTION": "Play a Melody."
  },
  "bard:HarmoniousVoice": {
    "NAME": "Harmonious Voice",
    "DESCRIPTION": "Whenever you queue a {Block Note} or {Buff Note} , gain !M! Temporary_HP."
  },
  "bard:DiscordantVoice": {
    "NAME": "Discordant Voice",
    "DESCRIPTION": "Whenever you queue a {Attack Note} or {Debuff Note} , deal !M! damage to a random enemy."
  },
  "bard:HideousLaughter": {
    "NAME": "Hideous Laughter",
    "DESCRIPTION": "Apply !M! Vulnerable and !M! Weak."
  },
  "bard:BucklerBash": {
    "NAME": "Buckler Bash",
    "DESCRIPTION": "Lose !M! Block. NL Deal !D! damage."
  },
  "bard:ViciousMockery": {
    "NAME": "Vicious Mockery",
    "DESCRIPTION": "Apply !M! Weak. NL Deal !D! damage."
  },
  "bard:BestowCurse": {
    "NAME": "Bestow Curse",
    "DESCRIPTION": "Enemy takes !M! damage at the start of each of its turns."
  },
  "bard:FeastOnFear": {
    "NAME": "Feast on Fear",
    "DESCRIPTION": "Gain !B! Block. NL If the enemy is Vulnerable, gain !M! Temporary_HP instead."
  },
  "bard:Thunderwave": {
    "NAME": "Thunderwave",
    "DESCRIPTION": "Deal !D! damage and apply !M! Weak to ALL enemies."
  },
  "bard:SongBolt": {
    "NAME": "Song Bolt",
    "DESCRIPTION": "Deal !D! damage for each Note you have queued. NL Clear your Note queue."
  },
  "bard:QuickSong": {
    "NAME": "Quick Song",
    "DESCRIPTION": "Discard a card. NL Queue Notes as if the card was played. NL Play a Melody."
  },
  "bard:TinyHut": {
    "NAME": "Tiny Hut",
    "DESCRIPTION": "Gain !B! Block. NL Draw 1 card for each {Block Note} you have queued.",
    "EXTENDED_DESCRIPTION": [
      " NL (",
      " {Block Note} queued.)"
    ]
  },
  "bard:Gamble": {
    "NAME": "Gamble",
    "DESCRIPTION": "Choose a card type (Attack/Skill/Power). NL Draw 1 card, if it is the chosen type, it costs 0 this turn."
  },
  "bard:DervishDance": {
    "NAME": "Dervish Dance",
    "DESCRIPTION": "Deal !D! damage to ALL enemies for each {Attack Note} you have queued.",
    "EXTENDED_DESCRIPTION": [
      " NL (",
      " {Attack Note} queued.)"
    ]
  },
  "bard:Parry": {
    "NAME": "Parry",
    "DESCRIPTION": "Gain !B! Block. NL Dexterity affects this card !M! times."
  },
  "bard:Balestra": {
    "NAME": "Balestra",
    "DESCRIPTION": "Deal !D! damage !M! times. NL This card's damage is affected by Dexterity instead of Strength."
  },
  "bard:Greatness": {
    "NAME": "Greatness",
    "DESCRIPTION": "Gain Inspiration 100.",
    "UPGRADE_DESCRIPTION": "Gain !M! Inspiration 100."
  },
  "bard:Invisibility": {
    "NAME": "Invisibility",
    "DESCRIPTION": "Gain !M! Intangible. NL Draw !M! more card next turn. NL Exhaust.",
    "UPGRADE_DESCRIPTION": "Gain !M! Intangible. NL Draw !M! more cards next turn. NL Exhaust.",
    "EXTENDED_DESCRIPTION": [
      "Greater Invisibility"
    ]
  },
  "bard:Advance": {
    "NAME": "Advance",
    "DESCRIPTION": "Gain [E]. NL Draw !M! cards. NL Lose [E] next turn.",
    "UPGRADE_DESCRIPTION": "Retain. NL "
  },
  "bard:Haste": {
    "NAME": "Haste",
    "DESCRIPTION": "Double your Dexterity. NL Exhaust.",
    "UPGRADE_DESCRIPTION": "Double your Dexterity. NL Exhaustive !stslib:ex!."
  },
  "bard:Heroism": {
    "NAME": "Heroism",
    "DESCRIPTION": "Gain !M! Temporary_HP and Inspiration !bard:M2!."
  }
}